myo_classification-0.0.2.data/scripts/data_loader.py
myo_classification-0.0.2.data/scripts/real_time.py
myo_classification-0.0.2.data/scripts/train_net.py
myo_classification-0.0.2.data/scripts/transfer_learn.py
scripts/__init__.py
scripts/common.py
scripts/data_loader.py
scripts/myo_feat_extract.py
scripts/myo_raw.py
scripts/pnn_train.py
scripts/real_time.py
scripts/semg_network.py
scripts/train_net.py
scripts/transfer_learn.py
myo_classification-0.0.2.dist-info/LICENSE
myo_classification-0.0.2.dist-info/METADATA
myo_classification-0.0.2.dist-info/WHEEL
myo_classification-0.0.2.dist-info/top_level.txt
myo_classification-0.0.2.dist-info/RECORD
